{"textures":{"0":"modelengine:entity/nocsy_fpv2_ghost"},"elements":[{"from":[7.0,6.846718,7.229402],"to":[9.0,8.846718,15.229403],"faces":{"east":{"uv":[10.125,9.625,11.125,9.875],"tintindex":0,"rotation":0,"texture":"#0"},"south":{"uv":[8.75,5.5,9.0,5.75],"tintindex":0,"rotation":0,"texture":"#0"},"north":{"uv":[8.75,5.125,9.0,5.375],"tintindex":0,"rotation":0,"texture":"#0"},"west":{"uv":[10.25,10.0,11.25,10.25],"tintindex":0,"rotation":0,"texture":"#0"},"up":{"uv":[3.875,6.0,3.625,5.0],"tintindex":0,"rotation":0,"texture":"#0"},"down":{"uv":[1.75,8.875,1.5,9.875],"tintindex":0,"rotation":0,"texture":"#0"}},"rotation":{"origin":[18.0,7.346718,10.729403],"angle":-22.5,"axis":"x"}},{"from":[4.0,7.846718,4.229402],"to":[19.0,7.846718,23.2294],"faces":{"up":{"uv":[1.875,2.375,0.0,0.0],"tintindex":0,"rotation":0,"texture":"#0"},"down":{"uv":[3.875,0.0,2.0,2.375],"tintindex":0,"rotation":0,"texture":"#0"}},"rotation":{"origin":[18.0,7.346718,10.729403],"angle":-22.5,"axis":"x"}}],"display":{"gui":{"rotation":[30,225,0]}}}