{"textures":{"0":"modelengine:entity/mushroom_cubee"},"elements":[{"from":[5.4975,6.922,7.9615],"to":[7.6535,9.077999,8.0385],"faces":{"east":{"uv":[9.015,0.515,9.125,0.985],"tintindex":0,"rotation":0,"texture":"#0"},"south":{"uv":[5.015,7.765,5.485,8.235],"tintindex":0,"rotation":0,"texture":"#0"},"north":{"uv":[1.515,7.765,1.985,8.235],"tintindex":0,"rotation":0,"texture":"#0"},"west":{"uv":[9.015,1.015,9.125,1.485],"tintindex":0,"rotation":0,"texture":"#0"},"up":{"uv":[9.485,1.625,9.015,1.515],"tintindex":0,"rotation":0,"texture":"#0"},"down":{"uv":[9.485,1.765,9.015,1.875],"tintindex":0,"rotation":0,"texture":"#0"}}},{"from":[8.3465,6.922,7.9615],"to":[10.502501,9.077999,8.0385],"faces":{"east":{"uv":[2.015,9.015,2.125,9.485],"tintindex":0,"rotation":0,"texture":"#0"},"south":{"uv":[8.015,0.515,8.485,0.985],"tintindex":0,"rotation":0,"texture":"#0"},"north":{"uv":[8.015,0.015,8.485,0.485],"tintindex":0,"rotation":0,"texture":"#0"},"west":{"uv":[9.015,2.015,9.125,2.485],"tintindex":0,"rotation":0,"texture":"#0"},"up":{"uv":[2.735,9.125,2.265,9.015],"tintindex":0,"rotation":0,"texture":"#0"},"down":{"uv":[9.485,2.515,9.015,2.625],"tintindex":0,"rotation":0,"texture":"#0"}}}],"display":{"gui":{"rotation":[30,225,0]}}}