{"textures":{"0":"modelengine:entity/oblivinonorb"},"elements":[{"from":[14.25,13.75,14.500001],"to":[0.25,0.74999905,1.5],"faces":{"east":{"uv":[13.75,0.5,14.375,1.125],"tintindex":0,"rotation":0,"texture":"#0"},"south":{"uv":[9.125,13.375,9.875,14.0],"tintindex":0,"rotation":0,"texture":"#0"},"north":{"uv":[0.0,13.375,0.75,14.0],"tintindex":0,"rotation":0,"texture":"#0"},"west":{"uv":[13.75,1.125,14.375,1.75],"tintindex":0,"rotation":0,"texture":"#0"},"up":{"uv":[14.125,10.125,13.375,9.5],"tintindex":0,"rotation":0,"texture":"#0"},"down":{"uv":[14.125,13.125,13.375,13.75],"tintindex":0,"rotation":0,"texture":"#0"}},"rotation":{"origin":[7.25,7.25,8.0],"angle":-45.0,"axis":"x"}}],"display":{"gui":{"rotation":[30,225,0]}}}